python_discord_logger/__init__.py
python_discord_logger/formatters.py
python_discord_logger/handlers.py
python_discord_logger/utils.py
python_discord_logger-1.2.0.dist-info/LICENSE
python_discord_logger-1.2.0.dist-info/WHEEL
python_discord_logger-1.2.0.dist-info/METADATA
python_discord_logger-1.2.0.dist-info/RECORD
