Metadata-Version: 2.1
Name: python-discord-logger
Version: 1.2.0
Summary: 
Author: Chanuk Kim
Author-email: cksdnr987@gmail.com
Requires-Python: >=3.9,<4.0
Classifier: Programming Language :: Python :: 3
Classifier: Programming Language :: Python :: 3.9
Requires-Dist: requests (>=2.25.1,<3.0.0)
